Metadata-Version: 2.1
Name: lektor-markdown-header-anchors
Version: 0.3.1
Summary: Lektor plugin that adds anchors and table of contents to markdown headers.
Home-page: http://github.com/lektor/lektor-markdown-header-anchors
Author: Armin Ronacher
Author-email: armin.ronacher@active-4.com
License: BSD
Keywords: Lektor plugin markdown static-site blog toc table-of-contents anchors headers
Platform: UNKNOWN
Classifier: Environment :: Plugins
Classifier: Environment :: Web Environment
Classifier: Framework :: Lektor
Classifier: Intended Audience :: Developers
Classifier: License :: OSI Approved :: BSD License
